local_stats/__init__.py
local_stats/cluster.py
local_stats/image.py
local_stats/io.py
local_stats-0.1.2.dist-info/LICENSE
local_stats-0.1.2.dist-info/METADATA
local_stats-0.1.2.dist-info/WHEEL
local_stats-0.1.2.dist-info/top_level.txt
local_stats-0.1.2.dist-info/RECORD
