Metadata-Version: 2.1
Name: local-stats
Version: 0.1.2
Summary: A python package for using local statistics to cluster significant signal in scientific images.
Author: Richard Brearton
Author-email: richardbrearton@gmail.com
License: MIT License
Platform: UNKNOWN
Classifier: Intended Audience :: Science/Research
Classifier: License :: OSI Approved :: MIT License
Classifier: Operating System :: Unix
Classifier: Operating System :: POSIX
Classifier: Programming Language :: Python
Classifier: Programming Language :: Python :: 3.9
Classifier: Programming Language :: Python :: 3.10
Classifier: Programming Language :: Python :: Implementation :: CPython
License-File: LICENSE
Requires-Dist: pillow (>=9.0.1)
Requires-Dist: scipy (>=1.8.0)
Requires-Dist: scikit-learn (>=1.0.2)
Requires-Dist: pywavelets (>=1.3.0)
